vpt_plugin_cellpose2/__init__.py
vpt_plugin_cellpose2/predict.py
vpt_plugin_cellpose2/segment.py
vpt_plugin_cellpose2-1.0.1.dist-info/LICENSE.md
vpt_plugin_cellpose2-1.0.1.dist-info/METADATA
vpt_plugin_cellpose2-1.0.1.dist-info/WHEEL
vpt_plugin_cellpose2-1.0.1.dist-info/RECORD
